[{"Record ID":"369051","First Name":"Louise Lewis","Last Name":"","Post Code":"4500","Club Category":"Rugby Union","Club Name":"Pine Rivers Pumas Rugby Union Club","Club Contact Name":"Louise Lewis","Club Email Address":"","Club Registration Number":"58147163774","Club State":"QLD","Club Verification":"Approved","Company Name":"","Confirm Club Email Address":"pumassecretary@gmail.com","Country\/Region":"","Email":"pumassecretary@gmail.com","Fundraising Link":"https:\/\/asf.org.au\/donate\/cadbury-cheer-and-a-half","Fundraising AU Customer":"","Postal Code":"","State\/Region":"","Upload Club Logo":"https:\/\/api-na1.hubspot.com\/form-integrations\/v1\/uploaded-files\/signed-url-redirect\/98399473532?portalId=22573492&sign=N6FcNm9qVPvzdZib8Y7H1xvl0-w%3D&conversionId=44364678-efea-44bf-935d-1b8d78f48462&filename=44364678-efea-44bf-935d-1b8d78f48462-upload_club_logo-Pine-Rivers-Pumas-Transparent.png"}]